embedl/__init__.py
embedl_sdk-2025.3.0.dist-info/METADATA
embedl_sdk-2025.3.0.dist-info/WHEEL
embedl_sdk-2025.3.0.dist-info/top_level.txt
embedl_sdk-2025.3.0.dist-info/RECORD
