Metadata-Version: 2.4
Name: embedl_sdk
Version: 2025.3.0
Summary: Efficient Deep Learning for the edge.
Requires-Python: >=3.10
